powerflow/__init__.py
powerflow/commands/__init__.py
powerflow/commands/htmx.py
powerflow/commands/make.py
powerflow/commands/remove_poetry/__init__.py
powerflow/commands/remove_poetry/config_converters.py
powerflow/commands/remove_poetry/utils.py
powerflow/commands/remove_poetry/virtualenv_.py
powerflow/commands/rm_migrations.py
powerflow/commands/work.py
powerflow/commands/write_env.py
powerflow/config.py
powerflow/main.py
powerflow/utils.py
powerflow-1.0.1.dist-info/LICENSE
powerflow-1.0.1.dist-info/METADATA
powerflow-1.0.1.dist-info/WHEEL
powerflow-1.0.1.dist-info/entry_points.txt
powerflow-1.0.1.dist-info/RECORD
