Metadata-Version: 2.1
Name: powerflow
Version: 1.0.1
Summary: A cli tool to bootstrap your django projects and enhance your development experience.
Home-page: https://github.com/Kodesio/Powerflow
License: MIT
Keywords: django,python,cookiecutter,project-template
Author: Aime DEGBEY
Author-email: team@kodesio.com
Requires-Python: >=3.8,<4.0
Classifier: Development Status :: 5 - Production/Stable
Classifier: Framework :: Django :: 4
Classifier: Framework :: Django :: 4.0
Classifier: Framework :: Django :: 4.1
Classifier: Intended Audience :: Developers
Classifier: License :: OSI Approved :: MIT License
Classifier: Natural Language :: English
Classifier: Programming Language :: Python
Classifier: Programming Language :: Python :: 3
Classifier: Programming Language :: Python :: 3.8
Classifier: Programming Language :: Python :: 3.9
Classifier: Programming Language :: Python :: 3.10
Classifier: Programming Language :: Python :: 3.11
Classifier: Programming Language :: Python :: 3.10
Classifier: Programming Language :: Python :: 3.11
Classifier: Programming Language :: Python :: 3.8
Classifier: Programming Language :: Python :: 3.9
Classifier: Programming Language :: Python :: Implementation :: CPython
Classifier: Programming Language :: Python :: Implementation :: PyPy
Requires-Dist: dict-deep (>=4.1.2,<5.0.0)
Requires-Dist: django (>=4)
Requires-Dist: httpx (>=0.23.3,<0.24.0)
Requires-Dist: python-dotenv (>=0.21.1,<0.22.0)
Requires-Dist: rich (>=13.3.1,<14.0.0)
Requires-Dist: tomli (>=2.0.1,<3.0.0) ; python_version < "3.11"
Requires-Dist: tomli-w (>=1.0.0,<2.0.0)
Requires-Dist: typer (>=0.7.0,<0.8.0)
Project-URL: Documentation, https://github.com/Kodesio/Powerflow
Project-URL: Repository, https://github.com/Kodesio/Powerflow
